Workbook

Sheet Infosys Assumptions
A1: INFOSYS LTD — DCF VALUATION MODEL | ASSUMPTIONS
A2: Self-Initiated | Krish Surana | FY2024 Base Year | Figures in ₹ Crore
A4: REVENUE & MARGIN ASSUMPTIONS
A5: Parameter | B5: FY2024A | C5: FY2025E | D5: FY2026E | E5: FY2027E | F5: FY2028E | G5: FY2029E | H5: Notes
A6: Revenue (₹ Cr) | B6: 153670 | H6: FY2024 Actuals
A7: Revenue Growth % | C7: 4% | D7: 6% | E7: 8% | F7: 8% | G7: 9% | H7: Recovery trajectory
A8: EBITDA Margin % | C8: 25% | D8: 25% | E8: 26% | F8: 26% | G8: 27% | H8: Stable IT margins
A9: Depreciation % Revenue | C9: 3% | D9: 3% | E9: 3% | F9: 3% | G9: 3% | H9: Asset-light model
A10: Tax Rate | C10: 26% | D10: 26% | E10: 26% | F10: 26% | G10: 26% | H10: Effective rate
A11: Capex % Revenue | C11: 2% | D11: 2% | E11: 2% | F11: 2% | G11: 2% | H11: Low capex IT
A12: Change in WC % Revenue | C12: 1% | D12: 1% | E12: 1% | F12: 1% | G12: 1% | H12: Tight WC management
A15: WACC BUILD
A16: Component | B16: Value | C16: Notes
A17: Risk Free Rate (10Y GSec) | B17: 7.2% | C17: India 10Y Bond
A18: Equity Risk Premium | B18: 5.5% | C18: Damodaran ERP
A19: Beta (5Y Monthly) | B19: 0.75 | C19: Defensive IT beta
A20: Cost of Equity | B20: 11.3% | C20: CAPM: Rf + β*ERP
A21: Cost of Debt (Pre-tax) | B21: 7.5% | C21: Minimal debt
A22: Tax Rate | B22: 26%
A23: Cost of Debt (Post-tax) | B23: 5.6%
A24: Debt Weight | B24: 10% | C24: Net cash company
A25: Equity Weight | B25: 90%
A26: WACC | B26: 10.7% | C26: Rounded to 11%

Sheet Infosys Financial Model
A1: INFOSYS LTD — INTEGRATED 3-STATEMENT MODEL + FCFF
A2: Figures in ₹ Crore | FY2024 Actuals + FY2025-29 Projections
A4: P&L STATEMENT | B4: FY2024A | C4: FY2025E | D4: FY2026E | E4: FY2027E | F4: FY2028E | G4: FY2029E
A5: Revenue | B5: 153670 | C5: =B6*1.04 | D5: =C6*1.06 | E5: =D6*1.08 | F5: =E6*1.08 | G5: =F6*1.09
A6: Growth % | C6: =(C6-B6)/B6 | D6: =(D6-C6)/C6 | E6: =(E6-D6)/D6 | F6: =(F6-E6)/E6 | G6: =(G6-F6)/F6
A7: EBITDA | C7: =C6*0.25 | D7: =D6*0.25 | E7: =E6*0.26 | F7: =F6*0.26 | G7: =G6*0.27
A8: EBITDA Margin % | C8: =C8/C6 | D8: =D8/D6 | E8: =E8/E6 | F8: =F8/F6 | G8: =G8/G6
A9: Depreciation | C9: =C6*0.03 | D9: =D6*0.03 | E9: =E6*0.03 | F9: =F6*0.03 | G9: =G6*0.03
A10: EBIT | C10: =C8-C10 | D10: =D8-D10 | E10: =E8-E10 | F10: =F8-F10 | G10: =G8-G10
A11: Interest / Other Income | C11: =C6*0.005 | D11: =D6*0.005 | E11: =E6*0.005 | F11: =F6*0.005 | G11: =G6*0.005
A12: PBT | C12: =C11+C12 | D12: =D11+D12 | E12: =E11+E12 | F12: =F11+F12 | G12: =G11+G12
A13: Tax (26%) | C13: =C13*0.26 | D13: =D13*0.26 | E13: =E13*0.26 | F13: =F13*0.26 | G13: =G13*0.26
A14: PAT | C14: =C13-C14 | D14: =D13-D14 | E14: =E13-E14 | F14: =F13-F14 | G14: =G13-G14
A17: FREE CASH FLOW TO FIRM (FCFF)
A18: EBIT (from P&L) | C18: =C11 | D18: =D11 | E18: =E11 | F18: =F11 | G18: =G11
A19: Tax on EBIT (26%) | C19: =C19*0.26 | D19: =D19*0.26 | E19: =E19*0.26 | F19: =F19*0.26 | G19: =G19*0.26
A20: NOPAT | C20: =C19-C20 | D20: =D19-D20 | E20: =E19-E20 | F20: =F19-F20 | G20: =G19-G20
A21: Add: Depreciation | C21: =C10 | D21: =D10 | E21: =E10 | F21: =F10 | G21: =G10
A22: Less: Capex | C22: =C6*0.02 | D22: =D6*0.02 | E22: =E6*0.02 | F22: =F6*0.02 | G22: =G6*0.02
A23: Less: Change in WC | C23: =C6*0.01 | D23: =D6*0.01 | E23: =E6*0.01 | F23: =F6*0.01 | G23: =G6*0.01
A24: FCFF | C24: =C21+C22-C23-C24 | D24: =D21+D22-D23-D24 | E24: =E21+E22-E23-E24 | F24: =F21+F22-F23-F24 | G24: =G21+G22-G23-G24

Sheet Infosys DCF Valuation
A1: INFOSYS LTD — DCF VALUATION & INTRINSIC VALUE
A2: WACC: 11% | Terminal Growth: 4% | Figures in ₹ Crore
A4: Year | B4: FCFF (₹ Cr) | C4: Discount Factor | D4: PV of FCFF
A5: FY2025E | B5: ='Infosys Financial Model'!C25 | C5: =1/(1+0.11)^1 | D5: =B5*C5
A6: FY2026E | B6: ='Infosys Financial Model'!D25 | C6: =1/(1+0.11)^2 | D6: =B6*C6
A7: FY2027E | B7: ='Infosys Financial Model'!E25 | C7: =1/(1+0.11)^3 | D7: =B7*C7
A8: FY2028E | B8: ='Infosys Financial Model'!F25 | C8: =1/(1+0.11)^4 | D8: =B8*C8
A9: FY2029E | B9: ='Infosys Financial Model'!G25 | C9: =1/(1+0.11)^5 | D9: =B9*C9
A11: Sum of PV of FCFFs | B11: =SUM(D5:D9)
A12: Terminal Value | B12: =B9*(1+0.04)/(0.11-0.04)
A13: PV of Terminal Value | B13: =B12/(1+0.11)^5
A14: Enterprise Value (EV) | B14: =B11+B13
A15: Less: Net Debt / Add: Cash | B15: =-25000
A16: Equity Value | B16: =B14-B15
A17: Shares Outstanding (Cr) | B17: 420
A18: Intrinsic Value Per Share (₹) | B18: =B16/420
A19: Current Market Price (₹) | B19: 1450
A20: Upside / (Downside) % | B20: =(B18-B19)/B19
A21: Recommendation | B21: HOLD
A25: SENSITIVITY ANALYSIS — Intrinsic Value (₹) | WACC vs Terminal Growth
A26: WACC→ / TGR↓ | B26: 10.0% | C26: 10.5% | D26: 11.0% | E26: 11.5% | F26: 12.0%
A27: 3.0% | B27: 711 | C27: 658 | D27: 612 | E27: 571 | F27: 535
A28: 3.5% | B28: 762 | C28: 701 | D28: 648 | E28: 603 | F28: 563
A29: 4.0% | B29: 820 | C29: 750 | D29: 690 | E29: 639 | F29: 594
A30: 4.5% | B30: 889 | C30: 807 | D30: 738 | E30: 680 | F30: 629
A31: 5.0% | B31: 972 | C31: 875 | D31: 795 | E31: 727 | F31: 670
