Workbook

Sheet Infosys Assumptions
A1: INFOSYS LTD — DCF VALUATION MODEL | ASSUMPTIONS
A2: Self-Initiated | Krish Surana | FY2024 Base Year | Figures in ₹ Crore
A4: REVENUE & MARGIN ASSUMPTIONS
A5: Parameter | B5: FY2024A | C5: FY2025E | D5: FY2026E | E5: FY2027E | F5: FY2028E | G5: FY2029E | H5: Notes
A6: Revenue (₹ Cr) | B6: 153670 | H6: FY2024 Actuals
A7: Revenue Growth % | C7: 4% | D7: 6% | E7: 8% | F7: 8% | G7: 9% | H7: Recovery trajectory
A8: EBITDA Margin % | C8: 25% | D8: 25% | E8: 26% | F8: 26% | G8: 27% | H8: Stable IT margins
A9: Depreciation % Revenue | C9: 3% | D9: 3% | E9: 3% | F9: 3% | G9: 3% | H9: Asset-light model
A10: Tax Rate | C10: 26% | D10: 26% | E10: 26% | F10: 26% | G10: 26% | H10: Effective rate
A11: Capex % Revenue | C11: 2% | D11: 2% | E11: 2% | F11: 2% | G11: 2% | H11: Low capex IT
A12: Change in WC % Revenue | C12: 1% | D12: 1% | E12: 1% | F12: 1% | G12: 1% | H12: Tight WC management
A15: WACC BUILD
A16: Component | B16: Value | C16: Notes
A17: Risk Free Rate (10Y GSec) | B17: 7.2% | C17: India 10Y Bond
A18: Equity Risk Premium | B18: 5.5% | C18: Damodaran ERP
A19: Beta (5Y Monthly) | B19: 0.75 | C19: Defensive IT beta
A20: Cost of Equity | B20: 11.3% | C20: CAPM: Rf + β*ERP
A21: Cost of Debt (Pre-tax) | B21: 7.5% | C21: Minimal debt
A22: Tax Rate | B22: 26%
A23: Cost of Debt (Post-tax) | B23: 5.6%
A24: Debt Weight | B24: 10% | C24: Net cash company
A25: Equity Weight | B25: 90%
A26: WACC | B26: 10.7% | C26: Rounded to 11%

Sheet Infosys Financial Model
A1: INFOSYS LTD — INTEGRATED 3-STATEMENT MODEL + FCFF
A2: Figures in ₹ Crore | FY2024 Actuals + FY2025-29 Projections
A4: P&L STATEMENT | B4: FY2024A | C4: FY2025E | D4: FY2026E | E4: FY2027E | F4: FY2028E | G4: FY2029E
A5: Revenue | B5: 153670 | C5: =B6*1.04 | D5: =C6*1.06 | E5: =D6*1.08 | F5: =E6*1.08 | G5: =F6*1.09
A6: Growth % | C6: =(C6-B6)/B6 | D6: =(D6-C6)/C6 | E6: =(E6-D6)/D6 | F6: =(F6-E6)/E6 | G6: =(G6-F6)/F6
A7: EBITDA | C7: =C6*0.25 | D7: =D6*0.25 | E7: =E6*0.26 | F7: =F6*0.26 | G7: =G6*0.27
A8: EBITDA Margin % | C8: =C8/C6 | D8: =D8/D6 | E8: =E8/E6 | F8: =F8/F6 | G8: =G8/G6
A9: Depreciation | C9: =C6*0.03 | D9: =D6*0.03 | E9: =E6*0.03 | F9: =F6*0.03 | G9: =G6*0.03
A10: EBIT | C10: =C8-C10 | D10: =D8-D10 | E10: =E8-E10 | F10: =F8-F10 | G10: =G8-G10
A11: Interest / Other Income | C11: =C6*0.005 | D11: =D6*0.005 | E11: =E6*0.005 | F11: =F6*0.005 | G11: =G6*0.005
A12: PBT | C12: =C11+C12 | D12: =D11+D12 | E12: =E11+E12 | F12: =F11+F12 | G12: =G11+G12
A13: Tax (26%) | C13: =C13*0.26 | D13: =D13*0.26 | E13: =E13*0.26 | F13: =F13*0.26 | G13: =G13*0.26
A14: PAT | C14: =C13-C14 | D14: =D13-D14 | E14: =E13-E14 | F14: =F13-F14 | G14: =G13-G14
A17: FREE CASH FLOW TO FIRM (FCFF)
A18: EBIT (from P&L) | C18: =C11 | D18: =D11 | E18: =E11 | F18: =F11 | G18: =G11
A19: Tax on EBIT (26%) | C19: =C19*0.26 | D19: =D19*0.26 | E19: =E19*0.26 | F19: =F19*0.26 | G19: =G19*0.26
A20: NOPAT | C20: =C19-C20 | D20: =D19-D20 | E20: =E19-E20 | F20: =F19-F20 | G20: =G19-G20
A21: Add: Depreciation | C21: =C10 | D21: =D10 | E21: =E10 | F21: =F10 | G21: =G10
A22: Less: Capex | C22: =C6*0.02 | D22: =D6*0.02 | E22: =E6*0.02 | F22: =F6*0.02 | G22: =G6*0.02
A23: Less: Change in WC | C23: =C6*0.01 | D23: =D6*0.01 | E23: =E6*0.01 | F23: =F6*0.01 | G23: =G6*0.01
A24: FCFF | C24: =C21+C22-C23-C24 | D24: =D21+D22-D23-D24 | E24: =E21+E22-E23-E24 | F24: =F21+F22-F23-F24 | G24: =G21+G22-G23-G24

Sheet Infosys DCF Valuation
A1: INFOSYS LTD — DCF VALUATION & INTRINSIC VALUE
A2: WACC: 11% | Terminal Growth: 4% | Figures in ₹ Crore
A4: Year | B4: FCFF (₹ Cr) | C4: Discount Factor | D4: PV of FCFF
A5: FY2025E | B5: ='Infosys Financial Model'!C25 | C5: =1/(1+0.11)^1 | D5: =B5*C5
A6: FY2026E | B6: ='Infosys Financial Model'!D25 | C6: =1/(1+0.11)^2 | D6: =B6*C6
A7: FY2027E | B7: ='Infosys Financial Model'!E25 | C7: =1/(1+0.11)^3 | D7: =B7*C7
A8: FY2028E | B8: ='Infosys Financial Model'!F25 | C8: =1/(1+0.11)^4 | D8: =B8*C8
A9: FY2029E | B9: ='Infosys Financial Model'!G25 | C9: =1/(1+0.11)^5 | D9: =B9*C9
A11: Sum of PV of FCFFs | B11: =SUM(D5:D9)
A12: Terminal Value | B12: =B9*(1+0.04)/(0.11-0.04)
A13: PV of Terminal Value | B13: =B12/(1+0.11)^5
A14: Enterprise Value (EV) | B14: =B11+B13
A15: Less: Net Debt / Add: Cash | B15: =-25000
A16: Equity Value | B16: =B14-B15
A17: Shares Outstanding (Cr) | B17: 420
A18: Intrinsic Value Per Share (₹) | B18: =B16/420
A19: Current Market Price (₹) | B19: 1450
A20: Upside / (Downside) % | B20: =(B18-B19)/B19
A21: Recommendation | B21: HOLD
A25: SENSITIVITY ANALYSIS — Intrinsic Value (₹) | WACC vs Terminal Growth
A26: WACC→ / TGR↓ | B26: 10.0% | C26: 10.5% | D26: 11.0% | E26: 11.5% | F26: 12.0%
A27: 3.0% | B27: 711 | C27: 658 | D27: 612 | E27: 571 | F27: 535
A28: 3.5% | B28: 762 | C28: 701 | D28: 648 | E28: 603 | F28: 563
A29: 4.0% | B29: 820 | C29: 750 | D29: 690 | E29: 639 | F29: 594
A30: 4.5% | B30: 889 | C30: 807 | D30: 738 | E30: 680 | F30: 629
A31: 5.0% | B31: 972 | C31: 875 | D31: 795 | E31: 727 | F31: 670

Sheet FMCG FP&A Dashboard
A1: FMCG COMPANY — FP&A DASHBOARD | BUDGET vs ACTUALS
A2: Figures in ₹ Lakhs | FY2024 | Cost Centre Analysis
A4: DEPARTMENT-WISE BUDGET vs ACTUALS (₹ Lakhs)
A5: Department | B5: Budget (₹L) | C5: Actuals (₹L) | D5: Variance (₹L) | E5: Variance % | F5: Status | G5: Budget % | H5: Actual % | I5: vs Budget | J5: Action Required
A6: Sales & Marketing | B6: 450 | C6: 478 | D6: 28 | E6: 0.062222222 | F6: Over Budget | G6: 0.21428571 | H6: 0.22180974 | I6: 0.0075240305 | J6: Review spend
A7: Manufacturing | B7: 620 | C7: 598 | D7: -22 | E7: -0.035483871 | F7: Under Budget | G7: 0.2952381 | H7: 0.2774942 | I7: -0.017743896 | J7: Good
A8: Supply Chain | B8: 280 | C8: 312 | D8: 32 | E8: 0.11428571 | F8: Over Budget | G8: 0.13333333 | H8: 0.14477958 | I8: 0.011446249 | J8: Review spend
A9: R&D | B9: 150 | C9: 141 | D9: -9 | E9: -0.06 | F9: Under Budget | G9: 0.071428571 | H9: 0.065429234 | I9: -0.0059993371 | J9: Good
A10: Admin & Overhead | B10: 180 | C10: 195 | D10: 15 | E10: 0.083333333 | F10: Over Budget | G10: 0.085714286 | H10: 0.090487239 | I10: 0.0047729533 | J10: Review spend
A11: HR & Talent | B11: 120 | C11: 118 | D11: -2 | E11: -0.016666667 | F11: Under Budget | G11: 0.057142857 | H11: 0.054756381 | I11: -0.0023864766 | J11: Good
A12: IT & Digital | B12: 90 | C12: 97 | D12: 7 | E12: 0.077777778 | F12: Over Budget | G12: 0.042857143 | H12: 0.045011601 | I12: 0.0021544581 | J12: Review spend
A13: Finance & Legal | B13: 80 | C13: 79 | D13: -1 | E13: -0.0125 | F13: Under Budget | G13: 0.038095238 | H13: 0.036658933 | I13: -0.0014363054 | J13: Good
A14: Quality Control | B14: 60 | C14: 63 | D14: 3 | E14: 0.05 | F14: Over Budget | G14: 0.028571429 | H14: 0.029234339 | I14: 0.00066291018 | J14: Monitor
A15: Customer Service | B15: 70 | C15: 74 | D15: 4 | E15: 0.057142857 | F15: Over Budget | G15: 0.033333333 | H15: 0.034338747 | I15: 0.0010054138 | J15: Review spend
A16: TOTAL | B16: 2100 | C16: 2155 | D16: 55 | E16: 0.026190476 | F16: Over Budget
A18: PRODUCT LINE P&L — OVERHEAD ALLOCATION ANALYSIS
A19: Product Line | B19: Revenue | C19: Gross Profit | D19: GP Margin | E19: Overhead Alloc | F19: Net Profit | G19: NP Margin | H19: Status | I19: Recommendation | J19: Priority
A20: Personal Care - Premium | B20: 820 | C20: 369 | D20: 0.45 | E20: 185 | F20: 184 | G20: 0.22439024 | H20: Profitable | I20: Continue | J20: Low
A21: Personal Care - Mass | B21: 540 | C21: 189 | D21: 0.35 | E21: 162 | F21: 27 | G21: 0.05 | H21: Profitable | I21: Review pricing | J21: HIGH
A22: Home Care | B22: 380 | C22: 114 | D22: 0.3 | E22: 152 | F22: -38 | G22: -0.1 | H22: Loss Making | I22: Discontinue / Restructure | J22: HIGH
A23: Foods & Beverages | B23: 620 | C23: 248 | D23: 0.4 | E23: 124 | F23: 124 | G23: 0.2 | H23: Profitable | I23: Continue | J23: Low
A24: Baby Care | B24: 290 | C24: 130 | D24: 0.44827586 | E24: 116 | F24: 14 | G24: 0.048275862 | H24: Profitable | I24: Review pricing | J24: HIGH
A25: Health & Wellness | B25: 210 | C25: 84 | D25: 0.4 | E25: 84 | F25: 0 | G25: 0 | H25: Loss Making | I25: Discontinue / Restructure | J25: HIGH
A26: Private Label | B26: 180 | C26: 45 | D26: 0.25 | E26: 90 | F26: -45 | G26: -0.25 | H26: Loss Making | I26: Discontinue / Restructure | J26: HIGH
A29: KEY FINANCIAL KPIs
A30: Total Revenue (₹L) | B30: =SUM(B20:B26)
A31: Total Gross Profit (₹L) | B31: =SUM(C20:C26)
A32: Blended GP Margin % | B32: =B31/B30
A33: Total Overhead Allocated (₹L) | B33: =SUM(E20:E26)
A34: Total Net Profit (₹L) | B34: =SUM(F20:F26)
A35: Blended Net Margin % | B35: =B35/B30
A36: Loss-Making Product Lines | B36: 2 | C36: Home Care, Private Label
A37: Budget Overrun (₹L) | B37: 55
A38: Budget Overrun % | B38: 0.026190476
