Workbook

Sheet Assumptions
A1: RELIANCE INDUSTRIES LTD — DCF VALUATION MODEL | ASSUMPTIONS
A2: Self-Initiated Equity Research | Krish Surana | FY2024 Base Year
A4: REVENUE & MARGIN ASSUMPTIONS
A5: Parameter | B5: FY2024A | C5: FY2025E | D5: FY2026E | E5: FY2027E | F5: FY2028E | G5: FY2029E | H5: Notes
A6: Revenue (₹ Cr) | B6: 899041 | H6: FY2024 Actuals
A7: Revenue Growth % | C7: 9% | D7: 9% | E7: 10% | F7: 10% | G7: 8% | H7: 8-10% growth assumption
A8: EBITDA Margin % | C8: 17% | D8: 17% | E8: 18% | F8: 18% | G8: 19% | H8: 17-19% margin range
A9: Depreciation % of Revenue | C9: 4% | D9: 4% | E9: 4% | F9: 4% | G9: 4% | H9: Stable capex-heavy co.
A10: Tax Rate | C10: 25% | D10: 25% | E10: 25% | F10: 25% | G10: 25% | H10: Effective tax rate
A11: Capex % of Revenue | C11: 6% | D11: 6% | E11: 5% | F11: 5% | G11: 5% | H11: Moderate capex cycle
A12: Change in Working Capital % Rev | C12: 2% | D12: 2% | E12: 2% | F12: 2% | G12: 2% | H12: Working capital build
A14: DCF & WACC ASSUMPTIONS
A15: Parameter | B15: Value | C15: Notes
A16: WACC | B16: 10.0% | C16: Cost of equity + debt weighted
A17: Terminal Growth Rate | B17: 4.0% | C17: Long-term India GDP proxy
A18: Projection Period (Years) | B18: 5 | C18: FY2025E - FY2029E
A19: Net Debt (₹ Cr) | B19: 118984 | C19: FY2024 balance sheet
A20: Shares Outstanding (Cr) | B20: 676 | C20: As of FY2024
A23: WACC BUILD
A24: Component | B24: Value | C24: Notes
A25: Risk Free Rate (10Y GSec) | B25: 7.2% | C25: India 10Y Govt Bond
A26: Equity Risk Premium | B26: 5.5% | C26: Damodaran India ERP
A27: Beta | B27: 0.85 | C27: Reliance 5Y monthly beta
A28: Cost of Equity (CAPM) | B28: =B25+(B26*B27) | C28: Rf + β × ERP
A29: Cost of Debt (Pre-tax) | B29: 8.0% | C29: Weighted avg borrowing cost
A30: Tax Rate | B30: 25% | C30: Effective tax rate
A31: Cost of Debt (Post-tax) | B31: =B30*(1-B31) | C31: Pre-tax × (1 - Tax)
A32: Debt / (Debt + Equity) | B32: 35% | C32: Capital structure
A33: Equity / (Debt + Equity) | B33: 65% | C33: Capital structure
A34: WACC | B34: =B32*B33+B29*B34 | C34: Weighted average

Sheet Financial Model
A1: RELIANCE INDUSTRIES LTD — 3-STATEMENT FINANCIAL MODEL
A2: Figures in ₹ Crore | Source: Annual Reports, Self-Initiated Research
A4: P&L STATEMENT | B4: FY2024A | C4: FY2025E | D4: FY2026E | E4: FY2027E | F4: FY2028E | G4: FY2029E
A5: Revenue | B5: 899041 | C5: =B6*1.09 | D5: =C6*1.09 | E5: =D6*1.10 | F5: =E6*1.10 | G5: =F6*1.08
A6: Growth % | C6: =(C6-B6)/B6 | D6: =(D6-C6)/C6 | E6: =(E6-D6)/D6 | F6: =(F6-E6)/E6 | G6: =(G6-F6)/F6
A7: EBITDA | C7: =C6*0.17 | D7: =D6*0.17 | E7: =E6*0.18 | F7: =F6*0.18 | G7: =G6*0.19
A8: EBITDA Margin % | C8: =C8/C6 | D8: =D8/D6 | E8: =E8/E6 | F8: =F8/F6 | G8: =G8/G6
A9: Depreciation | C9: =C6*0.04 | D9: =D6*0.04 | E9: =E6*0.04 | F9: =F6*0.04 | G9: =G6*0.04
A10: EBIT | C10: =C8-C10 | D10: =D8-D10 | E10: =E8-E10 | F10: =F8-F10 | G10: =G8-G10
A11: Interest Expense | C11: =C6*0.01 | D11: =D6*0.01 | E11: =E6*0.01 | F11: =F6*0.01 | G11: =G6*0.01
A12: PBT | C12: =C11-C12 | D12: =D11-D12 | E12: =E11-E12 | F12: =F11-F12 | G12: =G11-G12
A13: Tax (25%) | C13: =C13*0.25 | D13: =D13*0.25 | E13: =E13*0.25 | F13: =F13*0.25 | G13: =G13*0.25
A14: PAT (Net Profit) | C14: =C13-C14 | D14: =D13-D14 | E14: =E13-E14 | F14: =F13-F14 | G14: =G13-G14
A17: FREE CASH FLOW TO FIRM (FCFF)
A18: EBIT | C18: =C11 | D18: =D11 | E18: =E11 | F18: =F11 | G18: =G11
A19: Less: Tax on EBIT | C19: =C19*0.25 | D19: =D19*0.25 | E19: =E19*0.25 | F19: =F19*0.25 | G19: =G19*0.25
A20: NOPAT | C20: =C19-C20 | D20: =D19-D20 | E20: =E19-E20 | F20: =F19-F20 | G20: =G19-G20
A21: Add: Depreciation | C21: =C10 | D21: =D10 | E21: =E10 | F21: =F10 | G21: =G10
A22: Less: Capex | C22: =C6*0.06 | D22: =D6*0.06 | E22: =E6*0.05 | F22: =F6*0.05 | G22: =G6*0.05
A23: Less: Change in WC | C23: =C6*0.02 | D23: =D6*0.02 | E23: =E6*0.02 | F23: =F6*0.02 | G23: =G6*0.02
A24: FCFF | C24: =C21+C22-C23-C24 | D24: =D21+D22-D23-D24 | E24: =E21+E22-E23-E24 | F24: =F21+F22-F23-F24 | G24: =G21+G22-G23-G24

Sheet DCF Valuation
A1: RELIANCE INDUSTRIES — DCF VALUATION & INTRINSIC VALUE
A2: Figures in ₹ Crore | WACC: 10% | Terminal Growth: 4%
A4: Year | B4: FCFF (₹ Cr) | C4: Discount Factor | D4: PV of FCFF (₹ Cr)
A5: FY2025E | B5: ='Financial Model'!C25 | C5: =1/(1+0.10)^1 | D5: =B5*C5
A6: FY2026E | B6: ='Financial Model'!D25 | C6: =1/(1+0.10)^2 | D6: =B6*C6
A7: FY2027E | B7: ='Financial Model'!E25 | C7: =1/(1+0.10)^3 | D7: =B7*C7
A8: FY2028E | B8: ='Financial Model'!F25 | C8: =1/(1+0.10)^4 | D8: =B8*C8
A9: FY2029E | B9: ='Financial Model'!G25 | C9: =1/(1+0.10)^5 | D9: =B9*C9
A11: Sum of PV of FCFF | B11: =SUM(D5:D9)
A12: Terminal Value (TV) | B12: =B9*(1+0.04)/(0.10-0.04)
A13: PV of Terminal Value | B13: =B12/(1+0.10)^5
A14: Enterprise Value (EV) | B14: =B11+B13
A15: Less: Net Debt (₹ Cr) | B15: 118984
A16: Equity Value (₹ Cr) | B16: =B14-B15
A17: Shares Outstanding (Cr) | B17: 676
A18: Intrinsic Value Per Share (₹) | B18: =B16/B17
A19: Current Market Price (₹) | B19: 2700
A20: Upside / (Downside) % | B20: =(B18-B19)/B19
A21: Recommendation | B21: HOLD
A25: SENSITIVITY ANALYSIS — Intrinsic Value (₹) | WACC vs Terminal Growth Rate
A26: WACC → / TGR ↓ | B26: 9.0% | C26: 9.5% | D26: 10.0% | E26: 10.5% | F26: 11.0%
A27: 3.0% | B27: 1930 | C27: 1737 | D27: 1572 | E27: 1430 | F27: 1306
A28: 3.5% | B28: 2121 | C28: 1895 | D28: 1705 | E28: 1543 | F28: 1404
A29: 4.0% | B29: 2349 | C29: 2082 | D29: 1860 | E29: 1674 | F29: 1515
A30: 4.5% | B30: 2629 | C30: 2306 | D30: 2044 | E30: 1826 | F30: 1643
A31: 5.0% | B31: 2978 | C31: 2581 | D31: 2264 | E31: 2007 | F31: 1793

Sheet Peer Comparison
A1: PEER COMPARISON — RELIANCE vs ONGC vs BHARTI AIRTEL
A3: Metric | B3: Reliance Industries | C3: ONGC | D3: Bharti Airtel | E3: Sector Median | F3: RIL vs Median | G3: Notes
A4: P/E (x) | B4: 23.5 | C4: 8.2 | D4: 31.4 | E4: =MEDIAN(B5,C5,D5) | F4: =B5-E5 | G4: RIL at premium to ONGC
A5: EV/EBITDA (x) | B5: 11.2 | C5: 4.8 | D5: 9.6 | E5: =MEDIAN(B6,C6,D6) | F5: =B6-E6 | G5: In line with sector
A6: P/BV (x) | B6: 2.1 | C6: 0.9 | D6: 4.2 | E6: =MEDIAN(B7,C7,D7) | F6: =B7-E7 | G6: Fair value range
A7: Revenue Growth % (5Y) | B7: 9.0% | C7: 6.0% | D7: 18.0% | E7: 9.0% | G7: Airtel fastest grower
A8: EBITDA Margin % | B8: 17.5% | C8: 28.0% | D8: 32.0% | E8: 28.0% | G8: RIL lowest margins
A9: ROE % | B9: 9.2% | C9: 14.0% | D9: 22.0% | E9: 14.0% | G9: ROE improvement needed
A10: Debt/Equity | B10: 0.45 | C10: 0.12 | D10: 1.8 | E10: =MEDIAN(B11,C11,D11) | F10: =B11-E11 | G10: Moderate leverage
A11: Dividend Yield % | B11: 0.4% | C11: 3.5% | D11: 0.5% | E11: 0.5% | G11: Low yield, growth play
A14: INVESTMENT RECOMMENDATION
A15: Recommendation | B15: HOLD
A16: Intrinsic Value Range (₹) | B16: 2,900 – 3,100
A17: Current Market Price (₹) | B17: 2,700
A18: Implied Upside | B18: 8 – 12%
A19: Rationale | B19: Fair value with growth priced in. JLR recovery + Jio monetisation key catalysts.
A20: Risk Factors | B20: Global O2C slowdown, 5G capex drag, retail competition from Tata/Amazon.
