Workbook

Sheet Raw_Data
A1: Indian Defense Sector - Peer Financial Data
A3: Company | B3: Ticker | C3: Market Cap (Rs Cr) | D3: Share Price (Rs) | E3: EV/EBITDA (x) | F3: P/E TTM (x) | G3: P/BV (x) | H3: ROE (%)
A4: Bharat Dynamics Ltd | B4: BDL | C4: 43421 | D4: 1205.1 | E4: 176.68 | F4: 105.09 | G4: 10.42 | H4: 13.74
A5: Hindustan Aeronautics Ltd | B5: HAL | C5: 296600 | E5: 31.55
A6: Mazagon Dock Shipbuilders Ltd | B6: MAZDOCK | C6: 103104 | E6: 35.91 | G6: 10.5
A7: Bharat Electronics Ltd | B7: BEL | C7: 304300 | D7: 416.25 | F7: 40.8
A9: Data sources (public, no Bloomberg or CapIQ used):
A10: BDL: Market cap, price, EV/EBITDA, P/E TTM, P/BV, ROE - Source: MarketsMojo, Q4 FY26 result analysis, 31 May 2026, https://www.marketsmojo.com/news/result-analysis/bharat-dynamics-q4-fy26-defence-psu-faces-revenue-contraction-amid-order-execution-challenges-4023388
A11: HAL, Mazagon Dock EV/EBITDA (peer comparison figures cited in same BDL article) - Source: MarketsMojo, 31 May 2026, same article as above
A12: Mazagon Dock market cap, P/BV - Source: Screener.in company page, accessed July 2026, https://www.screener.in/company/MAZDOCK/consolidated/
A13: BEL market cap, price - Source: Yahoo Finance, BDL.NS peer comparison table, 28 May 2026, https://finance.yahoo.com/quote/BDL.NS/
A14: BEL forward P/E (40.8x) and 5 year average (20.7x) - Source: Nirmal Bang via BusinessToday, 15 April 2025, https://www.businesstoday.in/markets/stocks/story/mazagon-dock-hal-bdl-bel-share-price-targets-for-9-defence-stocks-ahead-of-q4-results-471974-2025-04-15
A15: Blank cells indicate the metric was not available from the public source at the time of research and has been left out rather than estimated.
A16: Data points were pulled on different dates due to public source availability. This is a limitation of using free sources instead of a live terminal, and is disclosed in Summary_Insights.

Sheet Comps_Analysis
A1: Relative Valuation - Comp Table
A3: Company | B3: EV/EBITDA (x) | C3: P/E TTM (x) | D3: P/BV (x) | E3: ROE (%) | F3: Premium/Discount to Peer Avg EV/EBITDA (%)
A4: =Raw_Data!A4 -> Bharat Dynamics Ltd | B4: =IF(Raw_Data!E4="","",Raw_Data!E4) -> 176.68 | C4: =IF(Raw_Data!F4="","",Raw_Data!F4) -> 105.09 | D4: =IF(Raw_Data!G4="","",Raw_Data!G4) -> 10.42 | E4: =IF(Raw_Data!H4="","",Raw_Data!H4) -> 13.74 | F4: =(B4-$B$9)/$B$9 -> 4.238067
A5: =Raw_Data!A5 -> Hindustan Aeronautics Ltd | B5: =IF(Raw_Data!E5="","",Raw_Data!E5) -> 31.55 | C5: =IF(Raw_Data!F5="","",Raw_Data!F5) | D5: =IF(Raw_Data!G5="","",Raw_Data!G5) | E5: =IF(Raw_Data!H5="","",Raw_Data!H5)
A6: =Raw_Data!A6 -> Mazagon Dock Shipbuilders Ltd | B6: =IF(Raw_Data!E6="","",Raw_Data!E6) -> 35.91 | C6: =IF(Raw_Data!F6="","",Raw_Data!F6) | D6: =IF(Raw_Data!G6="","",Raw_Data!G6) -> 10.5 | E6: =IF(Raw_Data!H6="","",Raw_Data!H6)
A7: =Raw_Data!A7 -> Bharat Electronics Ltd | B7: =IF(Raw_Data!E7="","",Raw_Data!E7) | C7: =IF(Raw_Data!F7="","",Raw_Data!F7) -> 40.8 | D7: =IF(Raw_Data!G7="","",Raw_Data!G7) | E7: =IF(Raw_Data!H7="","",Raw_Data!H7)
A9: Peer Average EV/EBITDA (HAL, Mazagon Dock) | B9: =AVERAGE(B5:B6) -> 33.73
A11: EV/EBITDA and P/E for BEL and P/E, ROE for HAL/Mazagon Dock were not available from public sources at the time of research and are left blank rather than estimated.

Sheet Summary_Insights
A1: Key Findings
A3: 1. Bharat Dynamics (BDL) trades at an EV/EBITDA of 176.68x, which is roughly five times the peer average of ~34x set by Hindustan Aeronautics (31.55x) and Mazagon Dock (35.91x).
A4: 2. BDL carries this premium despite an average ROE of just 13.74%, the lowest return profile in the peer set, and despite a 58.50% year on year decline in Q4 FY26 net profit.
A5: 3. The valuation gap suggests the market is pricing in a strong recovery in execution and order book conversion for BDL that has not yet shown up in recent quarterly results.
A6: 4. Mazagon Dock and HAL trade at more conservative multiples despite more consistent recent execution, which is the more defensible entry point of the four names on a pure valuation basis.
A8: Methodology
A9: Data was sourced from public financial news and data platforms (MarketsMojo, Screener.in, Yahoo Finance, BusinessToday), not Bloomberg Terminal or CapIQ.
A10: Raw data was structured and cleaned in the Raw_Data sheet to simulate a Power Query style extract, transform, load step.
A11: The Comps_Analysis sheet uses live formulas (not hardcoded values) referencing Raw_Data, similar to how Power Pivot measures would reference a data model.
A12: Peer average and premium/discount calculations use Excel formulas so the model updates automatically if the Raw_Data sheet is refreshed with newer figures.
A14: Limitations
A15: Data points were pulled from different dates (April 2025 to May 2026) due to reliance on free public sources rather than a live terminal feed. This means the comparison is illustrative of the valuation gap, not a same day snapshot.
A16: Some metrics (EV/EBITDA for BEL, P/E and ROE for HAL and Mazagon Dock) were not available from the public sources used and have been left blank rather than filled with estimates.
